{
  "config": {
    "fixedOrder": true
  },
  "prototypes": [
    {
      "name": "Car",
      "accel": 2.6,
      "decel": 4.5,
      "length": 5.0,
      "maxSpeed": 19.44,
      "minGap": 2.5,
      "sigma": 0.5,
      "speedDeviation": 0.1,
      "tau": 1.0,
      "applications": ["org.eclipse.mosaic.app.npr.NprVehicleApp"],
      "adHoc": { "maxDistance": 140 }
    }
  ],
  "rsus": [
        {
            "name": "rsu_zona1",
            "position": { 
                "latitude": 0.000014, 
                "longitude": 0.008983 
            },
            "applications": [ "org.eclipse.mosaic.app.npr.NprRsuApp" ],
            "adHoc": { "maxDistance": 140 }
        },
        {
            "name": "rsu_zona2",
            "position": { 
                "latitude": -0.008139, 
                "longitude": 0.004704 
            },
            "applications": [ "org.eclipse.mosaic.app.npr.NprRsuApp" ],
            "adHoc": { "maxDistance": 140 }
        },
        {
            "name": "rsu_zona3",
            "position": { 
                "latitude": -0.005306, 
                "longitude": 0.013516 
            },
            "applications": [ "org.eclipse.mosaic.app.npr.NprRsuApp" ],
            "adHoc": { "maxDistance": 140 }
        }
    ]
}